{
    "probe_frame": "3",
    "probe_sub": "0.5",
    "fov": "45",
    "fps": "24",
    "gain": "12",
    "awb_r": "3.18",
    "awb_b": "1.45",
    "image": "vop_logo_mockup_400px.png",
    "cam_res": "2028x1520",
    "tiff_compression": "none",
    "p_mode": "smooth",
    "r_mode": "smooth",
    "c_mode": "smooth",
    "f1": "1",
    "p1": "0.0,0.0,-3.0",
    "r1": "0.0,0.0,0.0",
    "c1_hex": "#ffffff",
    "s1": "2",
    "sd1": "4",
    "ph1": "1.0",
    "f2": "24",
    "p2": "0.0,0.0,-100.0",
    "r2": "0.0,0.0,0.0",
    "c2_hex": "#ffffff",
    "s2": "4",
    "sd2": "4",
    "ph2": "1.0",
    "f3": "48",
    "p3": "0.0,0.0,-3",
    "r3": "0.0,0.0,0.0",
    "c3_hex": "#ffffff",
    "s3": "2",
    "sd3": "4",
    "ph3": "1.0",
    "last_sync": 1770761127.703253
}